odoo/addons/helpdesk_mgmt_solution/README.rst
odoo/addons/helpdesk_mgmt_solution/__init__.py
odoo/addons/helpdesk_mgmt_solution/__manifest__.py
odoo/addons/helpdesk_mgmt_solution/demo/helpdesk_solution_demo.xml
odoo/addons/helpdesk_mgmt_solution/i18n/helpdesk_mgmt_solution.pot
odoo/addons/helpdesk_mgmt_solution/models/__init__.py
odoo/addons/helpdesk_mgmt_solution/models/helpdesk_solution.py
odoo/addons/helpdesk_mgmt_solution/models/helpdesk_ticket.py
odoo/addons/helpdesk_mgmt_solution/security/ir.model.access.csv
odoo/addons/helpdesk_mgmt_solution/static/description/icon.png
odoo/addons/helpdesk_mgmt_solution/tests/__init__.py
odoo/addons/helpdesk_mgmt_solution/tests/test_solution.py
odoo/addons/helpdesk_mgmt_solution/views/helpdesk_solution_view.xml
odoo/addons/helpdesk_mgmt_solution/views/helpdesk_ticket_view.xml
odoo/addons/helpdesk_mgmt_solution/views/menu_view.xml
odoo/addons/helpdesk_mgmt_solution/wizard/__init__.py
odoo/addons/helpdesk_mgmt_solution/wizard/solution.py
odoo/addons/helpdesk_mgmt_solution/wizard/solution.xml
odoo11_addon_helpdesk_mgmt_solution-11.0.1.0.0.99.dev2.dist-info/METADATA
odoo11_addon_helpdesk_mgmt_solution-11.0.1.0.0.99.dev2.dist-info/WHEEL
odoo11_addon_helpdesk_mgmt_solution-11.0.1.0.0.99.dev2.dist-info/top_level.txt
odoo11_addon_helpdesk_mgmt_solution-11.0.1.0.0.99.dev2.dist-info/RECORD
